[
  {
    "id": "flow-SnagReport-approval",
    "name": "SnagReport Approval Flow",
    "edges": [
      {
        "id": "gen_1783276193379_13",
        "sourceNodeId": "gen_1783276193378_11",
        "targetNodeId": "gen_1783276193378_12"
      },
      {
        "id": "gen_1783276193379_15",
        "branch": "true",
        "sourceNodeId": "gen_1783276193378_12",
        "targetNodeId": "gen_1783276193379_14"
      },
      {
        "id": "gen_1783276193379_17",
        "sourceNodeId": "gen_1783276193379_14",
        "targetNodeId": "gen_1783276193379_16"
      },
      {
        "id": "gen_1783276193379_20",
        "sourceNodeId": "gen_1783276193379_18",
        "targetNodeId": "gen_1783276193379_19"
      }
    ],
    "nodes": [
      {
        "id": "gen_1783276193378_11",
        "type": "trigger",
        "label": "On SnagReport Submit",
        "trigger": {
          "type": "on-field-change",
          "fieldName": "status",
          "resourceName": "SnagReport"
        },
        "position": {
          "x": 300,
          "y": 50
        }
      },
      {
        "id": "gen_1783276193378_12",
        "type": "condition",
        "label": "Status = PendingCRS?",
        "position": {
          "x": 300,
          "y": 160
        },
        "condition": {
          "logic": "and",
          "rules": [
            {
              "field": "triggerData.status",
              "value": "2",
              "operator": "equals"
            }
          ]
        }
      },
      {
        "id": "gen_1783276193379_14",
        "type": "approval",
        "label": "SnagReport Approval",
        "approval": {
          "steps": [
            {
              "name": "Certifying Staff Review",
              "actions": [
                {
                  "type": "approve",
                  "label": "Certify & Close"
                },
                {
                  "type": "revise",
                  "label": "Return for Revision",
                  "requiredFields": [
                    "revisionNote"
                  ]
                }
              ],
              "assigneeType": "field",
              "assigneeValue": "certifyingStaffId"
            }
          ],
          "onCompleteEvent": "SnagReport-approval-completed",
          "revisionAssignee": "previous-step",
          "trackRevisionHistory": true
        },
        "position": {
          "x": 300,
          "y": 280
        }
      },
      {
        "id": "gen_1783276193379_16",
        "type": "action",
        "label": "Send Approval Email",
        "action": {
          "type": "send-email",
          "config": {
            "to": "{{assigneeEmail}}",
            "body": "<p>Sayın Certifying Staff,</p><p><strong>{{triggerData.title}}</strong> snag raporu CRS onayınızı beklemektedir.</p><p>ATA: {{triggerData.ataChapter}} | Kritiklik: {{triggerData.criticality}}</p>",
            "subject": "{{triggerData.title}} — CRS Onayı Bekleniyor",
            "contentType": "html"
          }
        },
        "position": {
          "x": 300,
          "y": 400
        }
      },
      {
        "id": "gen_1783276193379_18",
        "type": "trigger",
        "label": "On SnagReport Approved",
        "trigger": {
          "type": "manual",
          "resourceName": "SnagReport"
        },
        "position": {
          "x": 700,
          "y": 50
        }
      },
      {
        "id": "gen_1783276193379_19",
        "type": "action",
        "label": "Send Completion Email",
        "action": {
          "type": "send-email",
          "config": {
            "cc": "{{departmentEmails}}",
            "to": "{{creatorEmail}}",
            "body": "<p>{{triggerData.formNo}} numarali formun onay sureci tamamlanmistir.</p>",
            "subject": "{{triggerData.formNo}} — Tum onaylar tamamlandi",
            "contentType": "html"
          }
        },
        "position": {
          "x": 700,
          "y": 160
        }
      }
    ],
    "enabled": true,
    "createdAt": "2026-07-05T18:29:53.378Z",
    "updatedAt": "2026-07-05T18:29:53.378Z",
    "variables": [
      {
        "name": "assigneeEmail",
        "type": "string",
        "defaultValue": ""
      },
      {
        "name": "creatorEmail",
        "type": "string",
        "defaultValue": ""
      },
      {
        "name": "departmentEmails",
        "type": "string",
        "defaultValue": ""
      },
      {
        "name": "formLink",
        "type": "string",
        "defaultValue": ""
      }
    ],
    "description": "Auto-generated approval flow for SnagReport. Customize email templates and add conditions as needed.",
    "resourceName": "SnagReport"
  }
]